my_snaps/InlineMenu.py
my_snaps/MyUtils.py
my_snaps/__init__.py
my_snaps/bt_smart_balance.py
my_snaps/main.py
my_snaps/my_restore.py
my_snaps-1.0.9.dist-info/entry_points.txt
my_snaps-1.0.9.dist-info/licenses/LICENSE
my_snaps-1.0.9.dist-info/WHEEL
my_snaps-1.0.9.dist-info/METADATA
my_snaps-1.0.9.dist-info/RECORD
