Metadata-Version: 2.4
Name: my-snaps
Version: 1.0.9
Summary: Simple BTRFS Snapshot Tools
Keywords: BTRFS,snapshot,restore,balance
Author-email: Joe Defen <joedef@duck.com>
Requires-Python: >=3.8
Classifier: Programming Language :: Python :: 3
Classifier: License :: OSI Approved :: MIT License
Classifier: Operating System :: POSIX :: Linux
License-File: LICENSE
Requires-Dist: console-window >= 1.0.0
Project-URL: Bug Tracker, https://github.com/joedefen/my-snaps/issues
Project-URL: Homepage, https://github.com/joedefen/my-snaps
